awesome_cli/__init__.py
awesome_cli/__main__.py
awesome_cli/__version__.py
awesome_cli/application.py
awesome_cli/awesome_parser.py
awesome_cli/commands/__init__.py
awesome_cli/commands/awesome_cli_apps.py
awesome_cli/config.py
awesome_cli/data/agarrharr-awesome-cli-apps.md
awesome_cli-0.2.0.dist-info/entry_points.txt
awesome_cli-0.2.0.dist-info/LICENSE
awesome_cli-0.2.0.dist-info/WHEEL
awesome_cli-0.2.0.dist-info/METADATA
awesome_cli-0.2.0.dist-info/RECORD
