Metadata-Version: 2.1
Name: awesome-cli
Version: 0.2.0
Summary: Awesome CLI search
Home-page: https://github.com/mlouielu/awesome-cli
License: MIT
Author: Louie Lu
Author-email: git@louie.lu
Requires-Python: >=3.7,<4.0
Classifier: License :: OSI Approved :: MIT License
Classifier: Programming Language :: Python :: 3
Classifier: Programming Language :: Python :: 3.7
Classifier: Programming Language :: Python :: 3.8
Classifier: Programming Language :: Python :: 3.9
Requires-Dist: cleo (>=0.8.1,<0.9.0)
Requires-Dist: colorful (>=0.5.4,<0.6.0)
Requires-Dist: lxml (>=4.6.3,<5.0.0)
Requires-Dist: mistune (>=0.8.4,<0.9.0)
Requires-Dist: prompt-toolkit (>=3.0.19,<4.0.0)
